README.rst
setup.py
django_uuid_upload_path.egg-info/PKG-INFO
django_uuid_upload_path.egg-info/SOURCES.txt
django_uuid_upload_path.egg-info/dependency_links.txt
django_uuid_upload_path.egg-info/top_level.txt
django_uuid_upload_path.egg-info/zip-safe
uuid_upload_path/__init__.py
uuid_upload_path/storage.py
uuid_upload_path/tests.py
uuid_upload_path/uuid.py