Metadata-Version: 1.1
Name: django-uuid-upload-path
Version: 1.0.0
Summary: Generate short UUIDs and use them as paths for uploaded media files in Django.
Home-page: https://github.com/etianen/django-uuid-upload-path
Author: Dave Hall
Author-email: dave@etianen.com
License: BSD
Platform: UNKNOWN
Classifier: Development Status :: 5 - Production/Stable
Classifier: Environment :: Web Environment
Classifier: Framework :: Django
Classifier: Intended Audience :: Developers
Classifier: License :: OSI Approved :: BSD License
Classifier: Operating System :: OS Independent
Classifier: Programming Language :: Python
Classifier: Programming Language :: Python
Classifier: Programming Language :: Python :: 2
Classifier: Programming Language :: Python :: 2.6
Classifier: Programming Language :: Python :: 2.7
Classifier: Topic :: Internet :: WWW/HTTP
